setup.py
asymmetricbase/__init__.py
asymmetricbase/urls.py
asymmetricbase.views.egg-info/PKG-INFO
asymmetricbase.views.egg-info/SOURCES.txt
asymmetricbase.views.egg-info/dependency_links.txt
asymmetricbase.views.egg-info/namespace_packages.txt
asymmetricbase.views.egg-info/requires.txt
asymmetricbase.views.egg-info/top_level.txt
asymmetricbase/management/__init__.py
asymmetricbase/management/commands/__init__.py
asymmetricbase/management/commands/update_view_perms.py
asymmetricbase/views/__init__.py
asymmetricbase/views/base.py
asymmetricbase/views/errors.py
asymmetricbase/views/mixins/__init__.py
asymmetricbase/views/mixins/base.py
asymmetricbase/views/mixins/merge_attr.py
asymmetricbase/views/mixins/multi_format_response.py